petprep_hmc/__init__.py
petprep_hmc/bids.py
petprep_hmc/utils.py
petprep_hmc-0.0.9.dist-info/LICENSE
petprep_hmc-0.0.9.dist-info/METADATA
petprep_hmc-0.0.9.dist-info/WHEEL
petprep_hmc-0.0.9.dist-info/top_level.txt
petprep_hmc-0.0.9.dist-info/RECORD
